client_module/__init__.py
client_module/client_database.py
client_module/client_gui.py
client_module/main_client_window_ui.py
client_module/transport.py
common/__init__.py
common/decorators.py
common/descriptors.py
common/metaclasses.py
common/utils.py
mess_chat_123_client-0.0.1.dist-info/METADATA
mess_chat_123_client-0.0.1.dist-info/WHEEL
mess_chat_123_client-0.0.1.dist-info/top_level.txt
mess_chat_123_client-0.0.1.dist-info/RECORD
